stym/__init__.py
stym/exception.py
stym/stym.py
stym/symbols.py
stym-0.1.0.dist-info/LICENSE
stym-0.1.0.dist-info/METADATA
stym-0.1.0.dist-info/WHEEL
stym-0.1.0.dist-info/entry_points.txt
stym-0.1.0.dist-info/top_level.txt
stym-0.1.0.dist-info/RECORD
