Metadata-Version: 2.1
Name: stym
Version: 0.1.0
Summary: A tool to migrate playlists from Spotify to YouTubeMusic
Author-email: Avadhani Jonnavithula <avadhanij@outlook.com>
Project-URL: Homepage, https://github.com/avadhanij/stym
Classifier: Programming Language :: Python :: 3
Classifier: License :: OSI Approved :: MIT License
Classifier: Operating System :: OS Independent
Requires-Python: >=3.8
License-File: LICENSE
Requires-Dist: pexpect ==4.9.0
Requires-Dist: pyyaml ==6.0.1
Requires-Dist: requests ==2.32.3
Requires-Dist: spotipy ==2.22.1
Requires-Dist: ytmusicapi ==1.7.3
